location_ipfire_db_reader/__init__.py
location_ipfire_db_reader/database.py
location_ipfire_db_reader/database_reader.py
location_ipfire_db_reader/decompress_db.py
location_ipfire_db_reader/download_db.py
location_ipfire_db_reader/exceptions.py
location_ipfire_db_reader/interpret_location_db.py
location_ipfire_db_reader/ip_information.py
location_ipfire_db_reader-1.0.7.dist-info/LICENSE
location_ipfire_db_reader-1.0.7.dist-info/METADATA
location_ipfire_db_reader-1.0.7.dist-info/WHEEL
location_ipfire_db_reader-1.0.7.dist-info/RECORD
