Metadata-Version: 2.1
Name: location_ipfire_db_reader
Version: 1.0.7
Summary: Easily get the country code from an ip address.
License: MIT
Author: Steven Van Ingelgem
Author-email: steven@vaningelgem.be
Requires-Python: >=3.9
Classifier: License :: OSI Approved :: MIT License
Classifier: Programming Language :: Python :: 3
Classifier: Programming Language :: Python :: 3.9
Classifier: Programming Language :: Python :: 3.10
Classifier: Programming Language :: Python :: 3.11
Classifier: Programming Language :: Python :: 3.12
Requires-Dist: requests (>=2)
Project-URL: Source Code, https://github.com/svaningelgem/location_ipfire_db_reader
